awadb_client/__init__.py
awadb_client/awadb_api.py
awadb_client/client.py
awadb_client/py_idl/awadb_pb2.py
awadb_client/py_idl/awadb_pb2_grpc.py
awadb_client-0.0.9.dist-info/METADATA
awadb_client-0.0.9.dist-info/WHEEL
awadb_client-0.0.9.dist-info/top_level.txt
awadb_client-0.0.9.dist-info/RECORD
